{"sections":{"main":{"type":"retainer-services_template","settings":{"bread_crumb_back":"shopify:\/\/shop_images\/about-us-05.jpg","bread_title":"Retainer Services","contact_img":"shopify:\/\/shop_images\/contact_icon_b5039660-c4fc-45c7-a3ae-0254f5b60863.png","contact_title":"Contact Us","contact_desc":"<p>For more information and to customise a package that is right for your RTO. Email at:<a href=\"mailto:info@caqa.com.au\"><span style=\"text-decoration:underline\">info@caqa.com.au<\/span><\/a><\/p>"}}},"order":["main"]}